linkml_store/__init__.py
linkml_store/cli.py
linkml_store/constants.py
linkml_store/api/__init__.py
linkml_store/api/client.py
linkml_store/api/collection.py
linkml_store/api/config.py
linkml_store/api/database.py
linkml_store/api/queries.py
linkml_store/api/types.py
linkml_store/api/stores/__init__.py
linkml_store/api/stores/chromadb/__init__.py
linkml_store/api/stores/chromadb/chromadb_collection.py
linkml_store/api/stores/chromadb/chromadb_database.py
linkml_store/api/stores/dremio/__init__.py
linkml_store/api/stores/dremio/dremio_collection.py
linkml_store/api/stores/dremio/dremio_database.py
linkml_store/api/stores/dremio/mappings.py
linkml_store/api/stores/dremio_rest/__init__.py
linkml_store/api/stores/dremio_rest/dremio_rest_collection.py
linkml_store/api/stores/dremio_rest/dremio_rest_database.py
linkml_store/api/stores/duckdb/__init__.py
linkml_store/api/stores/duckdb/duckdb_collection.py
linkml_store/api/stores/duckdb/duckdb_database.py
linkml_store/api/stores/duckdb/mappings.py
linkml_store/api/stores/filesystem/__init__.py
linkml_store/api/stores/filesystem/filesystem_collection.py
linkml_store/api/stores/filesystem/filesystem_database.py
linkml_store/api/stores/hdf5/__init__.py
linkml_store/api/stores/hdf5/hdf5_collection.py
linkml_store/api/stores/hdf5/hdf5_database.py
linkml_store/api/stores/ibis/__init__.py
linkml_store/api/stores/ibis/ibis_collection.py
linkml_store/api/stores/ibis/ibis_database.py
linkml_store/api/stores/mongodb/__init__.py
linkml_store/api/stores/mongodb/mongodb_collection.py
linkml_store/api/stores/mongodb/mongodb_database.py
linkml_store/api/stores/neo4j/__init__.py
linkml_store/api/stores/neo4j/neo4j_collection.py
linkml_store/api/stores/neo4j/neo4j_database.py
linkml_store/api/stores/solr/__init__.py
linkml_store/api/stores/solr/solr_collection.py
linkml_store/api/stores/solr/solr_database.py
linkml_store/api/stores/solr/solr_utils.py
linkml_store/graphs/__init__.py
linkml_store/graphs/graph_map.py
linkml_store-0.3.0.dist-info/METADATA
linkml_store-0.3.0.dist-info/WHEEL
linkml_store-0.3.0.dist-info/entry_points.txt
linkml_store-0.3.0.dist-info/licenses/LICENSE
linkml_store-0.3.0.dist-info/RECORD
