Metadata-Version: 2.4
Name: linkml-store
Version: 0.3.0
Summary: linkml-store
Author-email: Author 1 <author@org.org>
License-Expression: MIT
License-File: LICENSE
Requires-Python: <4.0,>=3.10
Requires-Dist: click
Requires-Dist: duckdb-engine>=0.11.2
Requires-Dist: duckdb>=0.10.1
Requires-Dist: google-cloud-bigquery
Requires-Dist: jinja2>=3.1.4
Requires-Dist: jsonlines>=4.0.0
Requires-Dist: jsonpatch>=1.33
Requires-Dist: jsonpath-ng
Requires-Dist: linkml-runtime>=1.8.0
Requires-Dist: multipledispatch
Requires-Dist: pandas>=2.2.1
Requires-Dist: pydantic>=2.0.0
Requires-Dist: pymongo>=4.11
Requires-Dist: pystow>=0.5.4
Requires-Dist: python-dotenv>=1.0.1
Requires-Dist: sqlalchemy
Requires-Dist: tabulate
Requires-Dist: xmltodict>=0.13.0
Provides-Extra: all
Requires-Dist: google-cloud-bigquery; extra == 'all'
Requires-Dist: linkml-map; extra == 'all'
Requires-Dist: linkml-renderer; extra == 'all'
Requires-Dist: linkml>=1.8.0; extra == 'all'
Requires-Dist: llm; extra == 'all'
Requires-Dist: neo4j; extra == 'all'
Requires-Dist: networkx; extra == 'all'
Requires-Dist: py2neo; extra == 'all'
Requires-Dist: tiktoken; extra == 'all'
Provides-Extra: analytics
Requires-Dist: matplotlib; extra == 'analytics'
Requires-Dist: pandas; extra == 'analytics'
Requires-Dist: plotly; extra == 'analytics'
Requires-Dist: seaborn; extra == 'analytics'
Provides-Extra: app
Requires-Dist: streamlit>=1.32.2; extra == 'app'
Provides-Extra: bigquery
Requires-Dist: google-cloud-bigquery; extra == 'bigquery'
Provides-Extra: dremio
Requires-Dist: pyarrow; extra == 'dremio'
Provides-Extra: fastapi
Requires-Dist: fastapi; extra == 'fastapi'
Requires-Dist: uvicorn; extra == 'fastapi'
Provides-Extra: frictionless
Requires-Dist: frictionless; extra == 'frictionless'
Provides-Extra: h5py
Requires-Dist: h5py; extra == 'h5py'
Provides-Extra: ibis
Requires-Dist: gcsfs; extra == 'ibis'
Requires-Dist: ibis-framework[duckdb,examples]>=9.3.0; extra == 'ibis'
Requires-Dist: multipledispatch; extra == 'ibis'
Provides-Extra: llm
Requires-Dist: llm; extra == 'llm'
Requires-Dist: tiktoken; extra == 'llm'
Provides-Extra: map
Requires-Dist: linkml-map>=0.3.9; extra == 'map'
Requires-Dist: ucumvert>=0.2.0; extra == 'map'
Provides-Extra: mongodb
Requires-Dist: pymongo; extra == 'mongodb'
Provides-Extra: neo4j
Requires-Dist: neo4j; extra == 'neo4j'
Requires-Dist: networkx; extra == 'neo4j'
Requires-Dist: py2neo; extra == 'neo4j'
Provides-Extra: pyarrow
Requires-Dist: pyarrow; extra == 'pyarrow'
Provides-Extra: pyreadr
Requires-Dist: pyreadr; extra == 'pyreadr'
Provides-Extra: rdf
Requires-Dist: lightrdf; extra == 'rdf'
Provides-Extra: renderer
Requires-Dist: linkml-renderer; extra == 'renderer'
Provides-Extra: scipy
Requires-Dist: scikit-learn; extra == 'scipy'
Requires-Dist: scipy; extra == 'scipy'
Provides-Extra: tests
Requires-Dist: black>=24.0.0; extra == 'tests'
Requires-Dist: ruff>=0.6.2; extra == 'tests'
Provides-Extra: validation
Requires-Dist: linkml>=1.8.0; extra == 'validation'
